[
  {
    "key": "ctrl+j",
    "command": "problems.action.focusProblemsFromFilter",
    "when": "problemsFilterFocus"
  },
  {
    "key": "space",
    "command": "vspacecode.space",
    "when": "activeEditorGroupEmpty && focusedView == '' && !whichkeyActive && !inputFocus"
  },
  {
    "key": "space",
    "command": "vspacecode.space",
    "when": "sideBarFocus && !inputFocus && !whichkeyActive"
  },
  {
    "key": "tab",
    "command": "extension.vim_tab",
    "when": "editorFocus && vim.active && !inDebugRepl && vim.mode != 'Insert' && editorLangId != 'magit'"
  },
  {
    "key": "tab",
    "command": "-extension.vim_tab",
    "when": "editorFocus && vim.active && !inDebugRepl && vim.mode != 'Insert'"
  },
  {
    "key": "r",
    "command": "renameFile",
    "when": "explorerViewletVisible && filesExplorerFocus && !explorerResourceIsRoot && !explorerResourceReadonly && !inputFocus"
  },
  {
    "key": "enter",
    "command": "-renameFile",
    "when": "explorerViewletVisible && filesExplorerFocus && !explorerResourceIsRoot && !explorerResourceReadonly && !inputFocus"
  },
  {
    "key": "l",
    "command": "list.toggleExpand",
    "when": "explorerViewletVisible && filesExplorerFocus && !inputFocus"
  },
  {
    "key": "y",
    "command": "filesExplorer.copy",
    "when": "explorerViewletVisible && filesExplorerFocus && !inputFocus"
  },
  {
    "key": "x",
    "command": "filesExplorer.cut",
    "when": "explorerViewletVisible && filesExplorerFocus && !inputFocus"
  },
  {
    "key": "p",
    "command": "filesExplorer.paste",
    "when": "explorerViewletVisible && filesExplorerFocus && !inputFocus"
  },
  {
    "key": "d",
    "command": "deleteFile",
    "when": "explorerViewletVisible && filesExplorerFocus && !inputFocus"
  },
  {
    "key": "h",
    "command": "list.collapse",
    "when": "explorerViewletVisible && filesExplorerFocus && !inputFocus"
  },
  {
    "key": "a",
    "command": "explorer.newFile",
    "when": "filesExplorerFocus && !inputFocus"
  },
  {
    "key": "shift+a",
    "command": "explorer.newFolder",
    "when": "filesExplorerFocus && !inputFocus"
  },
  {
    "key": "x",
    "command": "magit.discard-at-point",
    "when": "editorTextFocus && editorLangId == 'magit' && vim.mode =~ /^(?!SearchInProgressMode|CommandlineInProgress).*$/"
  },
  {
    "key": "k",
    "command": "-magit.discard-at-point"
  },
  {
    "key": "-",
    "command": "magit.reverse-at-point",
    "when": "editorTextFocus && editorLangId == 'magit' && vim.mode =~ /^(?!SearchInProgressMode|CommandlineInProgress).*$/"
  },
  {
    "key": "v",
    "command": "-magit.reverse-at-point"
  },
  {
    "key": "shift+-",
    "command": "magit.reverting",
    "when": "editorTextFocus && editorLangId == 'magit' && vim.mode =~ /^(?!SearchInProgressMode|CommandlineInProgress).*$/"
  },
  {
    "key": "shift+v",
    "command": "-magit.reverting"
  },
  {
    "key": "shift+o",
    "command": "magit.resetting",
    "when": "editorTextFocus && editorLangId == 'magit' && vim.mode =~ /^(?!SearchInProgressMode|CommandlineInProgress).*$/"
  },
  {
    "key": "shift+x",
    "command": "-magit.resetting"
  },
  {
    "key": "x",
    "command": "-magit.reset-mixed"
  },
  {
    "key": "ctrl+u x",
    "command": "-magit.reset-hard"
  },
  {
    "key": "y",
    "command": "-magit.show-refs"
  },
  {
    "key": "y",
    "command": "vspacecode.showMagitRefMenu",
    "when": "editorTextFocus && editorLangId == 'magit' && vim.mode == 'Normal'"
  },
  {
    "key": "ctrl+j",
    "command": "workbench.action.quickOpenSelectNext",
    "when": "inQuickOpen"
  },
  {
    "key": "ctrl+l",
    "when": "sideBarFocus",
    "command": "workbench.action.focusActiveEditorGroup"
  },
  {
    "key": "ctrl+k",
    "command": "workbench.action.quickOpenSelectPrevious",
    "when": "inQuickOpen"
  },
  {
    "key": "ctrl+k",
    "command": "workbench.action.focusActiveEditorGroup",
    "when": "terminalFocus || problemFocus || problemsFilterFocus || focusedView == 'workbench.panel.markers.view'"
  },
  {
    "key": "ctrl+k",
    "command": "workbench.action.focusActiveEditorGroup",
    "when": "inDebugRepl && textInputFocus"
  },
  {
    "key": "ctrl+j",
    "command": "selectNextSuggestion",
    "when": "suggestWidgetMultipleSuggestions && suggestWidgetVisible && textInputFocus"
  },
  {
    "key": "alt+j",
    "command": "workbench.action.terminal.focus",
    "when": "!terminalFocus"
  },
  {
    "key": "ctrl+k",
    "command": "selectPrevSuggestion",
    "when": "suggestWidgetMultipleSuggestions && suggestWidgetVisible && textInputFocus"
  },
  {
    "key": "ctrl+l",
    "command": "acceptSelectedSuggestion",
    "when": "suggestWidgetMultipleSuggestions && suggestWidgetVisible && textInputFocus"
  },
  {
    "key": "ctrl+j",
    "command": "showNextParameterHint",
    "when": "editorFocus && parameterHintsMultipleSignatures && parameterHintsVisible"
  },
  {
    "key": "ctrl+k",
    "command": "showPrevParameterHint",
    "when": "editorFocus && parameterHintsMultipleSignatures && parameterHintsVisible"
  },
  {
    "key": "ctrl+h",
    "command": "file-browser.stepOut",
    "when": "inFileBrowser"
  },
  {
    "key": "ctrl+l",
    "command": "file-browser.stepIn",
    "when": "inFileBrowser"
  },
  {
    "key": "shift+enter",
    "command": "jupyter.execSelectionInteractive",
    "when": "editorTextFocus && editorLangId == 'python'"
  },
  {
    "key": "ctrl+shift+enter",
    "command": "jupyter.runFileInteractive"
  },
  {
    "key": "alt+left",
    "command": "-breadcrumbs.focusPrevious",
    "when": "breadcrumbsActive && breadcrumbsVisible"
  },
  {
    "key": "alt+right",
    "command": "-breadcrumbs.focusNext",
    "when": "breadcrumbsActive && breadcrumbsVisible"
  },
  {
    "key": "shift+l",
    "command": "breadcrumbs.focusNext",
    "when": "breadcrumbsActive && breadcrumbsVisible"
  },
  {
    "key": "right",
    "command": "-breadcrumbs.focusNext",
    "when": "breadcrumbsActive && breadcrumbsVisible"
  },
  {
    "key": "shift+h",
    "command": "breadcrumbs.focusPrevious",
    "when": "breadcrumbsActive && breadcrumbsVisible"
  },
  {
    "key": "left",
    "command": "-breadcrumbs.focusPrevious",
    "when": "breadcrumbsActive && breadcrumbsVisible"
  },
  {
    "key": "ctrl+j",
    "command": "search.focus.nextInputBox",
    "when": "inSearchEditor && inputBoxFocus || inputBoxFocus && searchViewletVisible"
  },
  {
    "key": "ctrl+k",
    "command": "workbench.action.findInFiles",
    "when": "fileMatchOrMatchFocus && searchViewletVisible"
  }
]